Workbook

Sheet Categorias
A1: CATEGORIA | B1: FLUXO DE CAIXA
A2: Recebimento de venda | B2: RECEITA
A3: Aluguel | B3: DESPESAS FIXAS
A4: Vale transporte | B4: DESPESAS FIXAS
A5: Fornecedor | B5: GASTOS VARIÁVEIS
A6: Salário | B6: DESPESAS FIXAS
A7: Material escritório/limpeza | B7: DESPESAS FIXAS
A8: Gás | B8: GASTOS VARIÁVEIS
A9: Combustível | B9: DESPESAS FIXAS
A10: Manutenção | B10: INVESTIMENTOS
A11: Impressão | B11: DESPESAS FIXAS
A12: Não Operacional | B12: NÃO OPERACIONAL
... A38: INSS | B38: DESPESAS FIXAS

Sheet FLUXO DE CAIXA  SIMPLIFICADO
B2: SOFIA MORAES MACEDO LEMOS
B4: Mês | C4: Entradas | D4: Saídas | E4: Saldo
B5: JANEIRO | C5: =SUM('JANEIRO'!F13:F462) | D5: =SUM('JANEIRO'!G13:G462) | E5: =C5-D5
B6: FEVEREIRO | C6: =SUM('FEVEREIRO'!F13:F462) | D6: =SUM('FEVEREIRO'!G13:G462) | E6: =C6-D6
B7: MARÇO | C7: =SUM('MARÇO'!F13:F462) | D7: =SUM('MARÇO'!G13:G462) | E7: =C7-D7
B8: ABRIL | C8: =SUM('ABRIL'!F13:F462) | D8: =SUM('ABRIL'!G13:G462) | E8: =C8-D8
B9: MAIO | C9: =SUM('MAIO'!F13:F462) | D9: =SUM('MAIO'!G13:G462) | E9: =C9-D9
B10: JUNHO | C10: =SUM('JUNHO'!F13:F462) | D10: =SUM('JUNHO'!G13:G462) | E10: =C10-D10
B11: JULHO | C11: =SUM('JULHO'!F13:F462) | D11: =SUM('JULHO'!G13:G462) | E11: =C11-D11
B12: AGOSTO | C12: =SUM('AGOSTO'!F13:F462) | D12: =SUM('AGOSTO'!G13:G462) | E12: =C12-D12
B13: SETEMBRO | C13: =SUM('SETEMBRO'!F13:F462) | D13: =SUM('SETEMBRO'!G13:G462) | E13: =C13-D13
B14: OUTUBRO | C14: =SUM('OUTUBRO'!F13:F462) | D14: =SUM('OUTUBRO'!G13:G462) | E14: =C14-D14
B15: NOVEMBRO | C15: =SUM('NOVEMBRO'!F13:F462) | D15: =SUM('NOVEMBRO'!G13:G462) | E15: =C15-D15
B16: DEZEMBRO | C16: =SUM('DEZEMBRO'!F13:F462) | D16: =SUM('DEZEMBRO'!G13:G462) | E16: =C16-D16
B17: TOTAL | C17: =SUM(C5:C16) | D17: =SUM(D5:D16) | E17: =C17-D17

Sheet JANEIRO
B2: HUGO ZANETTI ESTEVES BASTOS
B7: SALDO INICIAL: | G7: =0
B12: Data | C12: Descrição | D12: Categoria | E12: Fluxo de Caixa | F12: Entrada | G12: Saída | H12: Saldo
E13: =IF(ISERROR(VLOOKUP(D13,Categorias!A:B,2,0)),"",VLOOKUP(D13,Categorias!A:B,2,0)) | H13: =G7+F13-G13
E14: =IF(ISERROR(VLOOKUP(D14,Categorias!A:B,2,0)),"",VLOOKUP(D14,Categorias!A:B,2,0)) | H14: =H13+F14-G14
E15: =IF(ISERROR(VLOOKUP(D15,Categorias!A:B,2,0)),"",VLOOKUP(D15,Categorias!A:B,2,0)) | H15: =H14+F15-G15
E16: =IF(ISERROR(VLOOKUP(D16,Categorias!A:B,2,0)),"",VLOOKUP(D16,Categorias!A:B,2,0)) | H16: =H15+F16-G16
E17: =IF(ISERROR(VLOOKUP(D17,Categorias!A:B,2,0)),"",VLOOKUP(D17,Categorias!A:B,2,0)) | H17: =H16+F17-G17
E18: =IF(ISERROR(VLOOKUP(D18,Categorias!A:B,2,0)),"",VLOOKUP(D18,Categorias!A:B,2,0)) | H18: =H17+F18-G18
E19: =IF(ISERROR(VLOOKUP(D19,Categorias!A:B,2,0)),"",VLOOKUP(D19,Categorias!A:B,2,0)) | H19: =H18+F19-G19
E20: =IF(ISERROR(VLOOKUP(D20,Categorias!A:B,2,0)),"",VLOOKUP(D20,Categorias!A:B,2,0)) | H20: =H19+F20-G20
E21: =IF(ISERROR(VLOOKUP(D21,Categorias!A:B,2,0)),"",VLOOKUP(D21,Categorias!A:B,2,0)) | H21: =H20+F21-G21
E22: =IF(ISERROR(VLOOKUP(D22,Categorias!A:B,2,0)),"",VLOOKUP(D22,Categorias!A:B,2,0)) | H22: =H21+F22-G22
E23: =IF(ISERROR(VLOOKUP(D23,Categorias!A:B,2,0)),"",VLOOKUP(D23,Categorias!A:B,2,0)) | H23: =H22+F23-G23
E24: =IF(ISERROR(VLOOKUP(D24,Categorias!A:B,2,0)),"",VLOOKUP(D24,Categorias!A:B,2,0)) | H24: =H23+F24-G24
E25: =IF(ISERROR(VLOOKUP(D25,Categorias!A:B,2,0)),"",VLOOKUP(D25,Categorias!A:B,2,0)) | H25: =H24+F25-G25
... E462: =IF(ISERROR(VLOOKUP(D462,Categorias!A:B,2,0)),"",VLOOKUP(D462,Categorias!A:B,2,0)) | H462: =H461+F462-G462

Sheet FEVEREIRO
B2: CAMILA SIQUEIRA FERNANDES CARDOSO
B7: SALDO INICIAL: | G7: =0
B12: Data | C12: Descrição | D12: Categoria | E12: Fluxo de Caixa | F12: Entrada | G12: Saída | H12: Saldo
E13: =IF(ISERROR(VLOOKUP(D13,Categorias!A:B,2,0)),"",VLOOKUP(D13,Categorias!A:B,2,0)) | H13: =G7+F13-G13
E14: =IF(ISERROR(VLOOKUP(D14,Categorias!A:B,2,0)),"",VLOOKUP(D14,Categorias!A:B,2,0)) | H14: =H13+F14-G14
E15: =IF(ISERROR(VLOOKUP(D15,Categorias!A:B,2,0)),"",VLOOKUP(D15,Categorias!A:B,2,0)) | H15: =H14+F15-G15
E16: =IF(ISERROR(VLOOKUP(D16,Categorias!A:B,2,0)),"",VLOOKUP(D16,Categorias!A:B,2,0)) | H16: =H15+F16-G16
E17: =IF(ISERROR(VLOOKUP(D17,Categorias!A:B,2,0)),"",VLOOKUP(D17,Categorias!A:B,2,0)) | H17: =H16+F17-G17
E18: =IF(ISERROR(VLOOKUP(D18,Categorias!A:B,2,0)),"",VLOOKUP(D18,Categorias!A:B,2,0)) | H18: =H17+F18-G18
E19: =IF(ISERROR(VLOOKUP(D19,Categorias!A:B,2,0)),"",VLOOKUP(D19,Categorias!A:B,2,0)) | H19: =H18+F19-G19
E20: =IF(ISERROR(VLOOKUP(D20,Categorias!A:B,2,0)),"",VLOOKUP(D20,Categorias!A:B,2,0)) | H20: =H19+F20-G20
E21: =IF(ISERROR(VLOOKUP(D21,Categorias!A:B,2,0)),"",VLOOKUP(D21,Categorias!A:B,2,0)) | H21: =H20+F21-G21
E22: =IF(ISERROR(VLOOKUP(D22,Categorias!A:B,2,0)),"",VLOOKUP(D22,Categorias!A:B,2,0)) | H22: =H21+F22-G22
E23: =IF(ISERROR(VLOOKUP(D23,Categorias!A:B,2,0)),"",VLOOKUP(D23,Categorias!A:B,2,0)) | H23: =H22+F23-G23
E24: =IF(ISERROR(VLOOKUP(D24,Categorias!A:B,2,0)),"",VLOOKUP(D24,Categorias!A:B,2,0)) | H24: =H23+F24-G24
E25: =IF(ISERROR(VLOOKUP(D25,Categorias!A:B,2,0)),"",VLOOKUP(D25,Categorias!A:B,2,0)) | H25: =H24+F25-G25
... E462: =IF(ISERROR(VLOOKUP(D462,Categorias!A:B,2,0)),"",VLOOKUP(D462,Categorias!A:B,2,0)) | H462: =H461+F462-G462

Sheet MARÇO
B2: LUCAS IBRAHIM SALGADO ALMEIDA
B7: SALDO INICIAL: | G7: =0
B12: Data | C12: Descrição | D12: Categoria | E12: Fluxo de Caixa | F12: Entrada | G12: Saída | H12: Saldo
E13: =IF(ISERROR(VLOOKUP(D13,Categorias!A:B,2,0)),"",VLOOKUP(D13,Categorias!A:B,2,0)) | H13: =G7+F13-G13
E14: =IF(ISERROR(VLOOKUP(D14,Categorias!A:B,2,0)),"",VLOOKUP(D14,Categorias!A:B,2,0)) | H14: =H13+F14-G14
E15: =IF(ISERROR(VLOOKUP(D15,Categorias!A:B,2,0)),"",VLOOKUP(D15,Categorias!A:B,2,0)) | H15: =H14+F15-G15
E16: =IF(ISERROR(VLOOKUP(D16,Categorias!A:B,2,0)),"",VLOOKUP(D16,Categorias!A:B,2,0)) | H16: =H15+F16-G16
E17: =IF(ISERROR(VLOOKUP(D17,Categorias!A:B,2,0)),"",VLOOKUP(D17,Categorias!A:B,2,0)) | H17: =H16+F17-G17
E18: =IF(ISERROR(VLOOKUP(D18,Categorias!A:B,2,0)),"",VLOOKUP(D18,Categorias!A:B,2,0)) | H18: =H17+F18-G18
E19: =IF(ISERROR(VLOOKUP(D19,Categorias!A:B,2,0)),"",VLOOKUP(D19,Categorias!A:B,2,0)) | H19: =H18+F19-G19
E20: =IF(ISERROR(VLOOKUP(D20,Categorias!A:B,2,0)),"",VLOOKUP(D20,Categorias!A:B,2,0)) | H20: =H19+F20-G20
E21: =IF(ISERROR(VLOOKUP(D21,Categorias!A:B,2,0)),"",VLOOKUP(D21,Categorias!A:B,2,0)) | H21: =H20+F21-G21
E22: =IF(ISERROR(VLOOKUP(D22,Categorias!A:B,2,0)),"",VLOOKUP(D22,Categorias!A:B,2,0)) | H22: =H21+F22-G22
E23: =IF(ISERROR(VLOOKUP(D23,Categorias!A:B,2,0)),"",VLOOKUP(D23,Categorias!A:B,2,0)) | H23: =H22+F23-G23
E24: =IF(ISERROR(VLOOKUP(D24,Categorias!A:B,2,0)),"",VLOOKUP(D24,Categorias!A:B,2,0)) | H24: =H23+F24-G24
E25: =IF(ISERROR(VLOOKUP(D25,Categorias!A:B,2,0)),"",VLOOKUP(D25,Categorias!A:B,2,0)) | H25: =H24+F25-G25
... E462: =IF(ISERROR(VLOOKUP(D462,Categorias!A:B,2,0)),"",VLOOKUP(D462,Categorias!A:B,2,0)) | H462: =H461+F462-G462

Sheet ABRIL
B2: SOFIA BASTOS CALDEIRA AMARAL
B7: SALDO INICIAL: | G7: =0
B12: Data | C12: Descrição | D12: Categoria | E12: Fluxo de Caixa | F12: Entrada | G12: Saída | H12: Saldo
E13: =IF(ISERROR(VLOOKUP(D13,Categorias!A:B,2,0)),"",VLOOKUP(D13,Categorias!A:B,2,0)) | H13: =G7+F13-G13
E14: =IF(ISERROR(VLOOKUP(D14,Categorias!A:B,2,0)),"",VLOOKUP(D14,Categorias!A:B,2,0)) | H14: =H13+F14-G14
E15: =IF(ISERROR(VLOOKUP(D15,Categorias!A:B,2,0)),"",VLOOKUP(D15,Categorias!A:B,2,0)) | H15: =H14+F15-G15
E16: =IF(ISERROR(VLOOKUP(D16,Categorias!A:B,2,0)),"",VLOOKUP(D16,Categorias!A:B,2,0)) | H16: =H15+F16-G16
E17: =IF(ISERROR(VLOOKUP(D17,Categorias!A:B,2,0)),"",VLOOKUP(D17,Categorias!A:B,2,0)) | H17: =H16+F17-G17
E18: =IF(ISERROR(VLOOKUP(D18,Categorias!A:B,2,0)),"",VLOOKUP(D18,Categorias!A:B,2,0)) | H18: =H17+F18-G18
E19: =IF(ISERROR(VLOOKUP(D19,Categorias!A:B,2,0)),"",VLOOKUP(D19,Categorias!A:B,2,0)) | H19: =H18+F19-G19
E20: =IF(ISERROR(VLOOKUP(D20,Categorias!A:B,2,0)),"",VLOOKUP(D20,Categorias!A:B,2,0)) | H20: =H19+F20-G20
E21: =IF(ISERROR(VLOOKUP(D21,Categorias!A:B,2,0)),"",VLOOKUP(D21,Categorias!A:B,2,0)) | H21: =H20+F21-G21
E22: =IF(ISERROR(VLOOKUP(D22,Categorias!A:B,2,0)),"",VLOOKUP(D22,Categorias!A:B,2,0)) | H22: =H21+F22-G22
E23: =IF(ISERROR(VLOOKUP(D23,Categorias!A:B,2,0)),"",VLOOKUP(D23,Categorias!A:B,2,0)) | H23: =H22+F23-G23
E24: =IF(ISERROR(VLOOKUP(D24,Categorias!A:B,2,0)),"",VLOOKUP(D24,Categorias!A:B,2,0)) | H24: =H23+F24-G24
E25: =IF(ISERROR(VLOOKUP(D25,Categorias!A:B,2,0)),"",VLOOKUP(D25,Categorias!A:B,2,0)) | H25: =H24+F25-G25
... E462: =IF(ISERROR(VLOOKUP(D462,Categorias!A:B,2,0)),"",VLOOKUP(D462,Categorias!A:B,2,0)) | H462: =H461+F462-G462

Sheet MAIO
B2: CLARA ZANETTI BRAGA NOGUEIRA
B7: SALDO INICIAL: | G7: =0
B12: Data | C12: Descrição | D12: Categoria | E12: Fluxo de Caixa | F12: Entrada | G12: Saída | H12: Saldo
E13: =IF(ISERROR(VLOOKUP(D13,Categorias!A:B,2,0)),"",VLOOKUP(D13,Categorias!A:B,2,0)) | H13: =G7+F13-G13
E14: =IF(ISERROR(VLOOKUP(D14,Categorias!A:B,2,0)),"",VLOOKUP(D14,Categorias!A:B,2,0)) | H14: =H13+F14-G14
E15: =IF(ISERROR(VLOOKUP(D15,Categorias!A:B,2,0)),"",VLOOKUP(D15,Categorias!A:B,2,0)) | H15: =H14+F15-G15
E16: =IF(ISERROR(VLOOKUP(D16,Categorias!A:B,2,0)),"",VLOOKUP(D16,Categorias!A:B,2,0)) | H16: =H15+F16-G16
E17: =IF(ISERROR(VLOOKUP(D17,Categorias!A:B,2,0)),"",VLOOKUP(D17,Categorias!A:B,2,0)) | H17: =H16+F17-G17
E18: =IF(ISERROR(VLOOKUP(D18,Categorias!A:B,2,0)),"",VLOOKUP(D18,Categorias!A:B,2,0)) | H18: =H17+F18-G18
E19: =IF(ISERROR(VLOOKUP(D19,Categorias!A:B,2,0)),"",VLOOKUP(D19,Categorias!A:B,2,0)) | H19: =H18+F19-G19
E20: =IF(ISERROR(VLOOKUP(D20,Categorias!A:B,2,0)),"",VLOOKUP(D20,Categorias!A:B,2,0)) | H20: =H19+F20-G20
E21: =IF(ISERROR(VLOOKUP(D21,Categorias!A:B,2,0)),"",VLOOKUP(D21,Categorias!A:B,2,0)) | H21: =H20+F21-G21
E22: =IF(ISERROR(VLOOKUP(D22,Categorias!A:B,2,0)),"",VLOOKUP(D22,Categorias!A:B,2,0)) | H22: =H21+F22-G22
E23: =IF(ISERROR(VLOOKUP(D23,Categorias!A:B,2,0)),"",VLOOKUP(D23,Categorias!A:B,2,0)) | H23: =H22+F23-G23
E24: =IF(ISERROR(VLOOKUP(D24,Categorias!A:B,2,0)),"",VLOOKUP(D24,Categorias!A:B,2,0)) | H24: =H23+F24-G24
E25: =IF(ISERROR(VLOOKUP(D25,Categorias!A:B,2,0)),"",VLOOKUP(D25,Categorias!A:B,2,0)) | H25: =H24+F25-G25
... E462: =IF(ISERROR(VLOOKUP(D462,Categorias!A:B,2,0)),"",VLOOKUP(D462,Categorias!A:B,2,0)) | H462: =H461+F462-G462

Sheet JUNHO
B2: VINICIUS HENRIQUES CALDEIRA PRADO
B7: SALDO INICIAL: | G7: =0
B12: Data | C12: Descrição | D12: Categoria | E12: Fluxo de Caixa | F12: Entrada | G12: Saída | H12: Saldo
E13: =IF(ISERROR(VLOOKUP(D13,Categorias!A:B,2,0)),"",VLOOKUP(D13,Categorias!A:B,2,0)) | H13: =G7+F13-G13
E14: =IF(ISERROR(VLOOKUP(D14,Categorias!A:B,2,0)),"",VLOOKUP(D14,Categorias!A:B,2,0)) | H14: =H13+F14-G14
E15: =IF(ISERROR(VLOOKUP(D15,Categorias!A:B,2,0)),"",VLOOKUP(D15,Categorias!A:B,2,0)) | H15: =H14+F15-G15
E16: =IF(ISERROR(VLOOKUP(D16,Categorias!A:B,2,0)),"",VLOOKUP(D16,Categorias!A:B,2,0)) | H16: =H15+F16-G16
E17: =IF(ISERROR(VLOOKUP(D17,Categorias!A:B,2,0)),"",VLOOKUP(D17,Categorias!A:B,2,0)) | H17: =H16+F17-G17
E18: =IF(ISERROR(VLOOKUP(D18,Categorias!A:B,2,0)),"",VLOOKUP(D18,Categorias!A:B,2,0)) | H18: =H17+F18-G18
E19: =IF(ISERROR(VLOOKUP(D19,Categorias!A:B,2,0)),"",VLOOKUP(D19,Categorias!A:B,2,0)) | H19: =H18+F19-G19
E20: =IF(ISERROR(VLOOKUP(D20,Categorias!A:B,2,0)),"",VLOOKUP(D20,Categorias!A:B,2,0)) | H20: =H19+F20-G20
E21: =IF(ISERROR(VLOOKUP(D21,Categorias!A:B,2,0)),"",VLOOKUP(D21,Categorias!A:B,2,0)) | H21: =H20+F21-G21
E22: =IF(ISERROR(VLOOKUP(D22,Categorias!A:B,2,0)),"",VLOOKUP(D22,Categorias!A:B,2,0)) | H22: =H21+F22-G22
E23: =IF(ISERROR(VLOOKUP(D23,Categorias!A:B,2,0)),"",VLOOKUP(D23,Categorias!A:B,2,0)) | H23: =H22+F23-G23
E24: =IF(ISERROR(VLOOKUP(D24,Categorias!A:B,2,0)),"",VLOOKUP(D24,Categorias!A:B,2,0)) | H24: =H23+F24-G24
E25: =IF(ISERROR(VLOOKUP(D25,Categorias!A:B,2,0)),"",VLOOKUP(D25,Categorias!A:B,2,0)) | H25: =H24+F25-G25
... E462: =IF(ISERROR(VLOOKUP(D462,Categorias!A:B,2,0)),"",VLOOKUP(D462,Categorias!A:B,2,0)) | H462: =H461+F462-G462

Sheet JULHO
B2: INES NEVES NOGUEIRA DUARTE
B7: SALDO INICIAL: | G7: =0
B12: Data | C12: Descrição | D12: Categoria | E12: Fluxo de Caixa | F12: Entrada | G12: Saída | H12: Saldo
E13: =IF(ISERROR(VLOOKUP(D13,Categorias!A:B,2,0)),"",VLOOKUP(D13,Categorias!A:B,2,0)) | H13: =G7+F13-G13
E14: =IF(ISERROR(VLOOKUP(D14,Categorias!A:B,2,0)),"",VLOOKUP(D14,Categorias!A:B,2,0)) | H14: =H13+F14-G14
E15: =IF(ISERROR(VLOOKUP(D15,Categorias!A:B,2,0)),"",VLOOKUP(D15,Categorias!A:B,2,0)) | H15: =H14+F15-G15
E16: =IF(ISERROR(VLOOKUP(D16,Categorias!A:B,2,0)),"",VLOOKUP(D16,Categorias!A:B,2,0)) | H16: =H15+F16-G16
E17: =IF(ISERROR(VLOOKUP(D17,Categorias!A:B,2,0)),"",VLOOKUP(D17,Categorias!A:B,2,0)) | H17: =H16+F17-G17
E18: =IF(ISERROR(VLOOKUP(D18,Categorias!A:B,2,0)),"",VLOOKUP(D18,Categorias!A:B,2,0)) | H18: =H17+F18-G18
E19: =IF(ISERROR(VLOOKUP(D19,Categorias!A:B,2,0)),"",VLOOKUP(D19,Categorias!A:B,2,0)) | H19: =H18+F19-G19
E20: =IF(ISERROR(VLOOKUP(D20,Categorias!A:B,2,0)),"",VLOOKUP(D20,Categorias!A:B,2,0)) | H20: =H19+F20-G20
E21: =IF(ISERROR(VLOOKUP(D21,Categorias!A:B,2,0)),"",VLOOKUP(D21,Categorias!A:B,2,0)) | H21: =H20+F21-G21
E22: =IF(ISERROR(VLOOKUP(D22,Categorias!A:B,2,0)),"",VLOOKUP(D22,Categorias!A:B,2,0)) | H22: =H21+F22-G22
E23: =IF(ISERROR(VLOOKUP(D23,Categorias!A:B,2,0)),"",VLOOKUP(D23,Categorias!A:B,2,0)) | H23: =H22+F23-G23
E24: =IF(ISERROR(VLOOKUP(D24,Categorias!A:B,2,0)),"",VLOOKUP(D24,Categorias!A:B,2,0)) | H24: =H23+F24-G24
E25: =IF(ISERROR(VLOOKUP(D25,Categorias!A:B,2,0)),"",VLOOKUP(D25,Categorias!A:B,2,0)) | H25: =H24+F25-G25
... E462: =IF(ISERROR(VLOOKUP(D462,Categorias!A:B,2,0)),"",VLOOKUP(D462,Categorias!A:B,2,0)) | H462: =H461+F462-G462

Sheet AGOSTO
B2: ALICE SALGADO NOGUEIRA ROCHA
B7: SALDO INICIAL: | G7: =0
B12: Data | C12: Descrição | D12: Categoria | E12: Fluxo de Caixa | F12: Entrada | G12: Saída | H12: Saldo
E13: =IF(ISERROR(VLOOKUP(D13,Categorias!A:B,2,0)),"",VLOOKUP(D13,Categorias!A:B,2,0)) | H13: =G7+F13-G13
E14: =IF(ISERROR(VLOOKUP(D14,Categorias!A:B,2,0)),"",VLOOKUP(D14,Categorias!A:B,2,0)) | H14: =H13+F14-G14
E15: =IF(ISERROR(VLOOKUP(D15,Categorias!A:B,2,0)),"",VLOOKUP(D15,Categorias!A:B,2,0)) | H15: =H14+F15-G15
E16: =IF(ISERROR(VLOOKUP(D16,Categorias!A:B,2,0)),"",VLOOKUP(D16,Categorias!A:B,2,0)) | H16: =H15+F16-G16
E17: =IF(ISERROR(VLOOKUP(D17,Categorias!A:B,2,0)),"",VLOOKUP(D17,Categorias!A:B,2,0)) | H17: =H16+F17-G17
E18: =IF(ISERROR(VLOOKUP(D18,Categorias!A:B,2,0)),"",VLOOKUP(D18,Categorias!A:B,2,0)) | H18: =H17+F18-G18
E19: =IF(ISERROR(VLOOKUP(D19,Categorias!A:B,2,0)),"",VLOOKUP(D19,Categorias!A:B,2,0)) | H19: =H18+F19-G19
E20: =IF(ISERROR(VLOOKUP(D20,Categorias!A:B,2,0)),"",VLOOKUP(D20,Categorias!A:B,2,0)) | H20: =H19+F20-G20
E21: =IF(ISERROR(VLOOKUP(D21,Categorias!A:B,2,0)),"",VLOOKUP(D21,Categorias!A:B,2,0)) | H21: =H20+F21-G21
E22: =IF(ISERROR(VLOOKUP(D22,Categorias!A:B,2,0)),"",VLOOKUP(D22,Categorias!A:B,2,0)) | H22: =H21+F22-G22
E23: =IF(ISERROR(VLOOKUP(D23,Categorias!A:B,2,0)),"",VLOOKUP(D23,Categorias!A:B,2,0)) | H23: =H22+F23-G23
E24: =IF(ISERROR(VLOOKUP(D24,Categorias!A:B,2,0)),"",VLOOKUP(D24,Categorias!A:B,2,0)) | H24: =H23+F24-G24
E25: =IF(ISERROR(VLOOKUP(D25,Categorias!A:B,2,0)),"",VLOOKUP(D25,Categorias!A:B,2,0)) | H25: =H24+F25-G25
... E462: =IF(ISERROR(VLOOKUP(D462,Categorias!A:B,2,0)),"",VLOOKUP(D462,Categorias!A:B,2,0)) | H462: =H461+F462-G462

Sheet SETEMBRO
B2: EVERTON DUARTE ALMEIDA RAMOS
B7: SALDO INICIAL: | G7: =0
B12: Data | C12: Descrição | D12: Categoria | E12: Fluxo de Caixa | F12: Entrada | G12: Saída | H12: Saldo
E13: =IF(ISERROR(VLOOKUP(D13,Categorias!A:B,2,0)),"",VLOOKUP(D13,Categorias!A:B,2,0)) | H13: =G7+F13-G13
E14: =IF(ISERROR(VLOOKUP(D14,Categorias!A:B,2,0)),"",VLOOKUP(D14,Categorias!A:B,2,0)) | H14: =H13+F14-G14
E15: =IF(ISERROR(VLOOKUP(D15,Categorias!A:B,2,0)),"",VLOOKUP(D15,Categorias!A:B,2,0)) | H15: =H14+F15-G15
E16: =IF(ISERROR(VLOOKUP(D16,Categorias!A:B,2,0)),"",VLOOKUP(D16,Categorias!A:B,2,0)) | H16: =H15+F16-G16
E17: =IF(ISERROR(VLOOKUP(D17,Categorias!A:B,2,0)),"",VLOOKUP(D17,Categorias!A:B,2,0)) | H17: =H16+F17-G17
E18: =IF(ISERROR(VLOOKUP(D18,Categorias!A:B,2,0)),"",VLOOKUP(D18,Categorias!A:B,2,0)) | H18: =H17+F18-G18
E19: =IF(ISERROR(VLOOKUP(D19,Categorias!A:B,2,0)),"",VLOOKUP(D19,Categorias!A:B,2,0)) | H19: =H18+F19-G19
E20: =IF(ISERROR(VLOOKUP(D20,Categorias!A:B,2,0)),"",VLOOKUP(D20,Categorias!A:B,2,0)) | H20: =H19+F20-G20
E21: =IF(ISERROR(VLOOKUP(D21,Categorias!A:B,2,0)),"",VLOOKUP(D21,Categorias!A:B,2,0)) | H21: =H20+F21-G21
E22: =IF(ISERROR(VLOOKUP(D22,Categorias!A:B,2,0)),"",VLOOKUP(D22,Categorias!A:B,2,0)) | H22: =H21+F22-G22
E23: =IF(ISERROR(VLOOKUP(D23,Categorias!A:B,2,0)),"",VLOOKUP(D23,Categorias!A:B,2,0)) | H23: =H22+F23-G23
E24: =IF(ISERROR(VLOOKUP(D24,Categorias!A:B,2,0)),"",VLOOKUP(D24,Categorias!A:B,2,0)) | H24: =H23+F24-G24
E25: =IF(ISERROR(VLOOKUP(D25,Categorias!A:B,2,0)),"",VLOOKUP(D25,Categorias!A:B,2,0)) | H25: =H24+F25-G25
... E462: =IF(ISERROR(VLOOKUP(D462,Categorias!A:B,2,0)),"",VLOOKUP(D462,Categorias!A:B,2,0)) | H462: =H461+F462-G462

Sheet OUTUBRO
B2: WANDA XAVIER JARDIM TAVARES
B7: SALDO INICIAL: | G7: =0
B12: Data | C12: Descrição | D12: Categoria | E12: Fluxo de Caixa | F12: Entrada | G12: Saída | H12: Saldo
E13: =IF(ISERROR(VLOOKUP(D13,Categorias!A:B,2,0)),"",VLOOKUP(D13,Categorias!A:B,2,0)) | H13: =G7+F13-G13
E14: =IF(ISERROR(VLOOKUP(D14,Categorias!A:B,2,0)),"",VLOOKUP(D14,Categorias!A:B,2,0)) | H14: =H13+F14-G14
E15: =IF(ISERROR(VLOOKUP(D15,Categorias!A:B,2,0)),"",VLOOKUP(D15,Categorias!A:B,2,0)) | H15: =H14+F15-G15
E16: =IF(ISERROR(VLOOKUP(D16,Categorias!A:B,2,0)),"",VLOOKUP(D16,Categorias!A:B,2,0)) | H16: =H15+F16-G16
E17: =IF(ISERROR(VLOOKUP(D17,Categorias!A:B,2,0)),"",VLOOKUP(D17,Categorias!A:B,2,0)) | H17: =H16+F17-G17
E18: =IF(ISERROR(VLOOKUP(D18,Categorias!A:B,2,0)),"",VLOOKUP(D18,Categorias!A:B,2,0)) | H18: =H17+F18-G18
E19: =IF(ISERROR(VLOOKUP(D19,Categorias!A:B,2,0)),"",VLOOKUP(D19,Categorias!A:B,2,0)) | H19: =H18+F19-G19
E20: =IF(ISERROR(VLOOKUP(D20,Categorias!A:B,2,0)),"",VLOOKUP(D20,Categorias!A:B,2,0)) | H20: =H19+F20-G20
E21: =IF(ISERROR(VLOOKUP(D21,Categorias!A:B,2,0)),"",VLOOKUP(D21,Categorias!A:B,2,0)) | H21: =H20+F21-G21
E22: =IF(ISERROR(VLOOKUP(D22,Categorias!A:B,2,0)),"",VLOOKUP(D22,Categorias!A:B,2,0)) | H22: =H21+F22-G22
E23: =IF(ISERROR(VLOOKUP(D23,Categorias!A:B,2,0)),"",VLOOKUP(D23,Categorias!A:B,2,0)) | H23: =H22+F23-G23
E24: =IF(ISERROR(VLOOKUP(D24,Categorias!A:B,2,0)),"",VLOOKUP(D24,Categorias!A:B,2,0)) | H24: =H23+F24-G24
E25: =IF(ISERROR(VLOOKUP(D25,Categorias!A:B,2,0)),"",VLOOKUP(D25,Categorias!A:B,2,0)) | H25: =H24+F25-G25
... E462: =IF(ISERROR(VLOOKUP(D462,Categorias!A:B,2,0)),"",VLOOKUP(D462,Categorias!A:B,2,0)) | H462: =H461+F462-G462

Sheet NOVEMBRO
B2: CAMILA LEMOS VALENTE DANTAS
B7: SALDO INICIAL: | G7: =0
B12: Data | C12: Descrição | D12: Categoria | E12: Fluxo de Caixa | F12: Entrada | G12: Saída | H12: Saldo
E13: =IF(ISERROR(VLOOKUP(D13,Categorias!A:B,2,0)),"",VLOOKUP(D13,Categorias!A:B,2,0)) | H13: =G7+F13-G13
E14: =IF(ISERROR(VLOOKUP(D14,Categorias!A:B,2,0)),"",VLOOKUP(D14,Categorias!A:B,2,0)) | H14: =H13+F14-G14
E15: =IF(ISERROR(VLOOKUP(D15,Categorias!A:B,2,0)),"",VLOOKUP(D15,Categorias!A:B,2,0)) | H15: =H14+F15-G15
E16: =IF(ISERROR(VLOOKUP(D16,Categorias!A:B,2,0)),"",VLOOKUP(D16,Categorias!A:B,2,0)) | H16: =H15+F16-G16
E17: =IF(ISERROR(VLOOKUP(D17,Categorias!A:B,2,0)),"",VLOOKUP(D17,Categorias!A:B,2,0)) | H17: =H16+F17-G17
E18: =IF(ISERROR(VLOOKUP(D18,Categorias!A:B,2,0)),"",VLOOKUP(D18,Categorias!A:B,2,0)) | H18: =H17+F18-G18
E19: =IF(ISERROR(VLOOKUP(D19,Categorias!A:B,2,0)),"",VLOOKUP(D19,Categorias!A:B,2,0)) | H19: =H18+F19-G19
E20: =IF(ISERROR(VLOOKUP(D20,Categorias!A:B,2,0)),"",VLOOKUP(D20,Categorias!A:B,2,0)) | H20: =H19+F20-G20
E21: =IF(ISERROR(VLOOKUP(D21,Categorias!A:B,2,0)),"",VLOOKUP(D21,Categorias!A:B,2,0)) | H21: =H20+F21-G21
E22: =IF(ISERROR(VLOOKUP(D22,Categorias!A:B,2,0)),"",VLOOKUP(D22,Categorias!A:B,2,0)) | H22: =H21+F22-G22
E23: =IF(ISERROR(VLOOKUP(D23,Categorias!A:B,2,0)),"",VLOOKUP(D23,Categorias!A:B,2,0)) | H23: =H22+F23-G23
E24: =IF(ISERROR(VLOOKUP(D24,Categorias!A:B,2,0)),"",VLOOKUP(D24,Categorias!A:B,2,0)) | H24: =H23+F24-G24
E25: =IF(ISERROR(VLOOKUP(D25,Categorias!A:B,2,0)),"",VLOOKUP(D25,Categorias!A:B,2,0)) | H25: =H24+F25-G25
... E462: =IF(ISERROR(VLOOKUP(D462,Categorias!A:B,2,0)),"",VLOOKUP(D462,Categorias!A:B,2,0)) | H462: =H461+F462-G462

Sheet DEZEMBRO
B2: KARINA CALDEIRA DUARTE HENRIQUES
B7: SALDO INICIAL: | G7: =0
B12: Data | C12: Descrição | D12: Categoria | E12: Fluxo de Caixa | F12: Entrada | G12: Saída | H12: Saldo
E13: =IF(ISERROR(VLOOKUP(D13,Categorias!A:B,2,0)),"",VLOOKUP(D13,Categorias!A:B,2,0)) | H13: =G7+F13-G13
E14: =IF(ISERROR(VLOOKUP(D14,Categorias!A:B,2,0)),"",VLOOKUP(D14,Categorias!A:B,2,0)) | H14: =H13+F14-G14
E15: =IF(ISERROR(VLOOKUP(D15,Categorias!A:B,2,0)),"",VLOOKUP(D15,Categorias!A:B,2,0)) | H15: =H14+F15-G15
E16: =IF(ISERROR(VLOOKUP(D16,Categorias!A:B,2,0)),"",VLOOKUP(D16,Categorias!A:B,2,0)) | H16: =H15+F16-G16
E17: =IF(ISERROR(VLOOKUP(D17,Categorias!A:B,2,0)),"",VLOOKUP(D17,Categorias!A:B,2,0)) | H17: =H16+F17-G17
E18: =IF(ISERROR(VLOOKUP(D18,Categorias!A:B,2,0)),"",VLOOKUP(D18,Categorias!A:B,2,0)) | H18: =H17+F18-G18
E19: =IF(ISERROR(VLOOKUP(D19,Categorias!A:B,2,0)),"",VLOOKUP(D19,Categorias!A:B,2,0)) | H19: =H18+F19-G19
E20: =IF(ISERROR(VLOOKUP(D20,Categorias!A:B,2,0)),"",VLOOKUP(D20,Categorias!A:B,2,0)) | H20: =H19+F20-G20
E21: =IF(ISERROR(VLOOKUP(D21,Categorias!A:B,2,0)),"",VLOOKUP(D21,Categorias!A:B,2,0)) | H21: =H20+F21-G21
E22: =IF(ISERROR(VLOOKUP(D22,Categorias!A:B,2,0)),"",VLOOKUP(D22,Categorias!A:B,2,0)) | H22: =H21+F22-G22
E23: =IF(ISERROR(VLOOKUP(D23,Categorias!A:B,2,0)),"",VLOOKUP(D23,Categorias!A:B,2,0)) | H23: =H22+F23-G23
E24: =IF(ISERROR(VLOOKUP(D24,Categorias!A:B,2,0)),"",VLOOKUP(D24,Categorias!A:B,2,0)) | H24: =H23+F24-G24
E25: =IF(ISERROR(VLOOKUP(D25,Categorias!A:B,2,0)),"",VLOOKUP(D25,Categorias!A:B,2,0)) | H25: =H24+F25-G25
... E462: =IF(ISERROR(VLOOKUP(D462,Categorias!A:B,2,0)),"",VLOOKUP(D462,Categorias!A:B,2,0)) | H462: =H461+F462-G462
